devicepilot/__init__.py
devicepilot/_format.py
devicepilot/batch.py
devicepilot/configure.py
devicepilot/post.py
devicepilot/validate.py
devicepilot-1.0.1.dist-info/LICENSE
devicepilot-1.0.1.dist-info/METADATA
devicepilot-1.0.1.dist-info/WHEEL
devicepilot-1.0.1.dist-info/top_level.txt
devicepilot-1.0.1.dist-info/RECORD
