Metadata-Version: 2.1
Name: devicepilot
Version: 1.0.1
Summary: DevicePilot SDK for IoT Analytics
Home-page: https://github.com/devicepilot/devicepilot-py
Author: DevicePilot
Author-email: tom.wallace@devicepilot.com
License: UNKNOWN
Platform: UNKNOWN
Classifier: Development Status :: 4 - Beta
Classifier: Intended Audience :: Developers
Classifier: Natural Language :: English
Classifier: Operating System :: OS Independent
Classifier: License :: OSI Approved :: MIT License
Classifier: Programming Language :: Python :: 3
Classifier: Topic :: Database :: Front-Ends
Classifier: Topic :: Home Automation
Classifier: Topic :: Internet
Classifier: Topic :: Scientific/Engineering :: Information Analysis
Classifier: Topic :: Scientific/Engineering :: Interface Engine/Protocol Translator
Classifier: Topic :: Software Development :: Libraries :: Python Modules
Classifier: Topic :: System :: Logging
Requires-Dist: requests
Provides-Extra: develop
Requires-Dist: pylint (==2.1.1) ; extra == 'develop'
Requires-Dist: pytest (==4.0.0) ; extra == 'develop'
Requires-Dist: responses (==0.10.4) ; extra == 'develop'
